quayadmin/__init__.py
quayadmin/_impl.py
quayadmin-0.1.2.dist-info/entry_points.txt
quayadmin-0.1.2.dist-info/LICENSE
quayadmin-0.1.2.dist-info/WHEEL
quayadmin-0.1.2.dist-info/METADATA
quayadmin-0.1.2.dist-info/RECORD
