Metadata-Version: 2.1
Name: quayadmin
Version: 0.1.2
Summary: Do administrative stuff on quay.io.
Home-page: https://github.com/jml/quay-admin
License: UNKNOWN
Author: Jonathan M. Lange
Author-email: jml@mumak.net
Classifier: License :: OSI Approved :: Apache Software License
Requires-Dist: attrs
Requires-Dist: treq
Requires-Dist: twisted[tls]
